ddmra/__init__.py
ddmra/_version.py
ddmra/analysis.py
ddmra/due.py
ddmra/filter.py
ddmra/info.py
ddmra/plotting.py
ddmra/utils.py
ddmra/workflows.py
ddmra/tests/__init__.py
ddmra/tests/test_utils.py
ddmra-0.0.1a0.dist-info/LICENSE
ddmra-0.0.1a0.dist-info/METADATA
ddmra-0.0.1a0.dist-info/WHEEL
ddmra-0.0.1a0.dist-info/top_level.txt
ddmra-0.0.1a0.dist-info/RECORD
