Metadata-Version: 2.1
Name: ddmra
Version: 0.0.1a0
Summary: A Python package for distance-dependent motion-related artifact (DDMRA) analysis.
Home-page: https://github.com/ME-ICA/ddmra
Author: Taylor Salo
Author-email: tsalo006@fiu.edu
Maintainer: Taylor Salo
Maintainer-email: tsalo006@fiu.edu
License: LGPL 2.1
Download-URL: https://github.com/tsalo/ddmra/archive/v0.0.1a.tar.gz
Platform: UNKNOWN
Classifier: Development Status :: 2 - Pre-Alpha
Classifier: Intended Audience :: Science/Research
Classifier: Topic :: Scientific/Engineering :: Information Analysis
Classifier: License :: OSI Approved :: GNU Library or Lesser General Public License (LGPL)
Classifier: Programming Language :: Python :: 3.6
Classifier: Programming Language :: Python :: 3.7
Classifier: Programming Language :: Python :: 3.8
Classifier: Programming Language :: Python :: 3.9
Requires-Python: >=3.6
Requires-Dist: joblib
Requires-Dist: nibabel
Requires-Dist: nilearn
Requires-Dist: numpy (>=1.15)
Requires-Dist: scipy (>=1.3.3)
Requires-Dist: seaborn
Provides-Extra: all
Requires-Dist: codecov ; extra == 'all'
Requires-Dist: flake8 (>=3.7) ; extra == 'all'
Requires-Dist: sphinx (>=1.5.3) ; extra == 'all'
Requires-Dist: flake8-isort ; extra == 'all'
Requires-Dist: pytest-cov ; extra == 'all'
Requires-Dist: sphinx-rtd-theme ; extra == 'all'
Requires-Dist: nbsphinx ; extra == 'all'
Requires-Dist: flake8-black ; extra == 'all'
Requires-Dist: pytest ; extra == 'all'
Requires-Dist: versioneer ; extra == 'all'
Requires-Dist: duecredit ; extra == 'all'
Requires-Dist: coverage (<5.0) ; extra == 'all'
Provides-Extra: dev
Requires-Dist: versioneer ; extra == 'dev'
Provides-Extra: doc
Requires-Dist: nbsphinx ; extra == 'doc'
Requires-Dist: sphinx (>=1.5.3) ; extra == 'doc'
Requires-Dist: sphinx-rtd-theme ; extra == 'doc'
Provides-Extra: duecredit
Requires-Dist: duecredit ; extra == 'duecredit'
Provides-Extra: tests
Requires-Dist: codecov ; extra == 'tests'
Requires-Dist: coverage (<5.0) ; extra == 'tests'
Requires-Dist: flake8 (>=3.7) ; extra == 'tests'
Requires-Dist: flake8-black ; extra == 'tests'
Requires-Dist: flake8-isort ; extra == 'tests'
Requires-Dist: pytest ; extra == 'tests'
Requires-Dist: pytest-cov ; extra == 'tests'
